{"pos": ["family", "good", "mild", "teach", "wealth", "present", "happy", "warmth", "beauty", "mile", "play", "mile", "mile", "know", "loyal", "mind", "magnificent", "quality", "art", "mile", "fine", "water", "great", "water", "great", "water", "young", "desire", "desire", "start", "water", "water", "water", "air", "let", "fair", "big", "feel", "easy", "smile", "feel", "soul", "dream", "funny", "good", "fine", "know", "air", "allow", "triumph", "save", "let", "know", "time", "save", "play", "wonder", "life", "time", "sleep", "pretty", "true", "grow", "drive", "bright", "big", "open", "life", "save", "fine", "kind", "admiration", "hero", "secure", "love", "drive", "bright", "forgive", "know", "know", "feel", "time", "allow", "generosity", "overcome", "clear", "forgive", "young", "sweet", "daring", "kind", "save", "victory", "allow", "kind", "delicate", "bloom", "sweet", "glad", "hello", "start", "light", "know", "know", "good"], "neg": ["terrible", "break", "oppressive", "dark", "bungle", "absurd", "scorn", "presumptuous", "steal", "strike", "tired", "dense", "wail", "blow", "fear", "lie", "tentatively", "loud", "burden", "fat", "scarce", "lie", "glare", "lie", "loud", "confused", "attack", "dim", "faint", "crack", "dirt", "strike", "lie", "motionless", "aggrieved", "suspicious", "foul", "shake", "fist", "difficult", "tease", "madden", "dark", "fiasco", "burn", "doubt", "spoil", "hurt", "fall", "hurt", "ignominiously", "drag", "crush", "wrinkle", "fierce", "dead", "poor", "mournfully", "sharply", "miss", "grief", "blame", "poor", "hurt", "break", "burn", "rumple", "regret", "reproach", "sorrow", "rascal", "scare", "death", "miserable", "sneak", "worry", "desperate", "afraid", "fierce", "blow", "slowly", "dark", "shame", "ignoble", "mockery", "sorry", "poor", "interrupt", "lie", "risk", "ruin", "hate", "muddy", "frighten", "sorry", "ashamed", "grief", "loss", "miss", "frighten", "hate", "impulsively", "hate", "risk", "wrest", "miss", "spite", "reproachful", "fear", "frighten", "terrible", "wild", "poor", "rip", "lose", "rip", "bully", "darkness"], "pos_scr": 9.933774834437086, "neg_scr": 11.163670766319774, "doc_len": 1057, "pos_frac": "Positives: 105/1057", "neg_frac": "Negatives: 118/1057"}